agent_runner/__init__.py
agent_runner-0.1.0.dist-info/licenses/LICENSE
agent_runner-0.1.0.dist-info/METADATA
agent_runner-0.1.0.dist-info/WHEEL
agent_runner-0.1.0.dist-info/top_level.txt
agent_runner-0.1.0.dist-info/RECORD
