Metadata-Version: 2.4
Name: agent-runner
Version: 0.1.0
Summary: open sourcing soon.
Author-email: Kamryn Ohly <kamryn@arcada.dev>
License: MIT
Requires-Python: >=3.8
License-File: LICENSE
Dynamic: license-file
